ontopic/__init__.py
ontopic/models/__init__.py
ontopic/models/pretrained/.keep
ontopic/models/TopicEmbedder.py
ontopic/models/utils.py
ontopic/utils.py
ontopic-0.1.0.dist-info/WHEEL
ontopic-0.1.0.dist-info/METADATA
ontopic-0.1.0.dist-info/RECORD
