Metadata-Version: 2.1
Name: ontopic
Version: 0.1.0
Summary: 
Home-page: https://github.com/GiveMeMoreData/ontopic
License: MIT
Author: GiveMeMoreData
Requires-Python: >=3.9,<4.0
Classifier: License :: OSI Approved :: MIT License
Classifier: Programming Language :: Python :: 3
Classifier: Programming Language :: Python :: 3.9
Classifier: Programming Language :: Python :: 3.10
Classifier: Programming Language :: Python :: 3.11
Requires-Dist: numpy (>=1.24.1,<2.0.0)
Requires-Dist: pandas (>=1.5.3,<2.0.0)
Requires-Dist: rdflib (>=6.2.0,<7.0.0)
Requires-Dist: scipy (>=1.10.0,<2.0.0); python_version >= "3.9" and python_version < "3.12"
Requires-Dist: torch (>=1.13.1,<2.0.0)
Requires-Dist: transformers (>=4.25.1,<5.0.0)
Project-URL: Repository, https://github.com/GiveMeMoreData/ontopic
